Workbook

Sheet CE 21-22
B2: FAR Polymers s.r.l. | E2: FAR Polymers s.r.l.
B3: CE consuntivo 2022 | C3: CONSUNTIVO | E3: Costi 2021 | F3: CONSUNTIVO
C4: Y1 | F4: Y1 | J4: 1, da dove arrivano alcuni numeri
B5: RICAVI DELLE VENDITE DI PRODOTTI FINITI | C5: 61294659
B6: RICAVI DELLE VENDITE DI MATERIE PRIME - RIADDEBITI MP A GAMMA | C6: 528226.63
B7: RICAVI CONTO LAVORAZIONE - GAMMA E POLIKEMIA | C7: 1877590.4
B8: ALTRI RICAVI E LAVORI IN ECONOMIA | C8: 120000
B9: VARIAZIONE PRODOTTI FINITI | C9: 500000
B10: A) TOTALE RICAVI PRODUZIONE | C10: =+SUM(C5:C9) -> 64320476
B11: ACQUISTO MATERIE PRIME | C11: -49370806 | J11: Tasso di cambio
B12: VARIAZIONE SCORTE | C12: 2500000 | J12: 1 | K12: euro | L12: "=" | M12: =1.17 -> 1.17 | N12: dollari
B13: B) TOTALE COSTI MATERIE PRIME | C13: =+C11+C12 -> -46870806 | J13: 1 | K13: dollaro | L13: "=" | M13: =J13/M12 -> 0.85470085 | N13: euro
B14: COSTO ENERGIA TOTALE | C14: -4152707.5 | E14: COSTO ENERGIA TOTALE | F14: -3950000 | M14: cambiare solo la cella arancio
B15: MATERIALI DI CONSUMO | C15: -175000 | E15: MATERIALI DI CONSUMO | F15: -150000
B16: PULIZIA E SMALTIMENTO RIFIUTI | C16: -519959.95 | E16: PULIZIA E SMALTIMENTO RIFIUTI | F16: -705000
B17: C) COSTI VARIABILI DI PRODUZIONE | C17: =SUM(C14:C16) -> -4847667.4 | E17: C) COSTI VARIABILI DI PRODUZIONE | F17: =SUM(F14:F16) -> -4805000
B18: TRASPORTI E ONERI DI VENDITA + ACQUISTO | C18: -1000000 | E18: TRASPORTI E ONERI DI VENDITA + ACQUISTO | F18: -1000000
B19: COSTO DI VENDITA - PROVVIGIONI-ENASARCO | C19: -550000 | E19: COSTO DI VENDITA - PROVVIGIONI-ENASARCO | F19: -550000
B20: D) TOTALE COSTI DI VENDITA | C20: =SUM(C18:C19) -> -1550000 | E20: D) TOTALE COSTI DI VENDITA | F20: =SUM(F18:F19) -> -1550000
B21: E) MARGINE OPERATIVO LORDO (A-B-C-D) | C21: =+C10+C13+C17+C20 -> 11052003
B22: COSTO DEL PERSONALE | C22: -5650000 | E22: COSTO DEL PERSONALE | F22: -5510785.9
B23: MANUTENZIONI | C23: -1100000 | E23: MANUTENZIONI | F23: -1200000
B24: ALTRI ONERI DEL PERSONALE | C24: -305000 | E24: ALTRI ONERI DEL PERSONALE | F24: -300000
B25: ASSICURAZIONI | C25: -145000 | E25: ASSICURAZIONI | F25: -148000
B26: CONSULENZE TECNICHE E CANONI ACQUE | C26: -307000 | E26: CONSULENZE TECNICHE E CANONI ACQUE | F26: -302000
B27: COSTO PER GODIMENTO DI BENI DI TERZI | C27: -209500 | E27: COSTO PER GODIMENTO DI BENI DI TERZI | F27: -207000
B28: F) TOTALE COSTI FISSI DI PRODUZIONE | C28: =SUM(C22:C27) -> -7716500 | E28: F) TOTALE COSTI FISSI DI PRODUZIONE | F28: =SUM(F22:F27) -> -7667785.9
B29: CONSULENZE E AMMINISTRATORI | C29: -556000 | E29: CONSULENZE E AMMINISTRATORI | F29: -550000
B30: SPESE UFFICIO VARIE E ONERI DIVERSI DI GESTIONE | C30: -297000 | E30: SPESE UFFICIO VARIE E ONERI DIVERSI DI GESTIONE | F30: -300000
B31: IMPOSTE E TASSE VARIE NON SUL REDDITO | C31: -98000 | E31: IMPOSTE E TASSE VARIE NON SUL REDDITO | F31: -100000
B32: G) TOTALE COSTI STRUTTURA COMM./AMM.VA | C32: =SUM(C29:C31) -> -951000 | E32: G) TOTALE COSTI STRUTTURA COMM./AMM.VA | F32: =SUM(F29:F31) -> -950000
B33: H) REDDITO OPERATIVO (EBITDA) (E-F-G) | C33: =+C21+C28+C32 -> 2384503
B34: AMMORTAMENTI IMMOBILIZZAZIONI IMMATERIALI | C34: -190000 | E34: AMMORTAMENTI IMMOBILIZZAZIONI IMMATERIALI | F34: -200000
B35: AMMORTAMENTI IMMOBILIZZAZIONI MATERIALI | C35: -810000 | E35: AMMORTAMENTI IMMOBILIZZAZIONI MATERIALI | F35: -750000
B36: SVALUTAZIONE CREDITI | C36: -25000 | E36: SVALUTAZIONE CREDITI | F36: -12000
B37: I) TOTALE AMMORTAMENTI | C37: =SUM(C34:C36) -> -1025000 | E37: I) TOTALE AMMORTAMENTI | F37: =SUM(F34:F36) -> -962000
B38: L) MARGINE OPERATIVO NETTO (EBIT) (H-I) | C38: =+C33+C37 -> 1359503
B39: (ONERI FINANZIARI) | C39: -140133.04
B40: PROVENTI FINANZIARI | C40: 3543.62
B41: M) ONERI E PROVENTI FINANZIARI NETTI | C41: =SUM(C39:C40) -> -136589.42
B42: N) REDDITO OPERATIVO GESTIONE CARATTERISTICA (L-M) | C42: =+C38+C41 -> 1222913.6
B43: (ONERI STRAORDINARI) | C43: -130503.97
B44: PROVENTI STRAORDINARI | C44: 0
B45: (SVALUTAZIONI-ACCANTONAMENTI) | C45: 0
B46: O) ONERI E PROVENTI STRAORDINARI NETTI | C46: =SUM(C43:C45) -> -130503.97
B47: P) RISULTATO ANTE IMPOSTE (N-O) | C47: =+C46+C42 -> 1092409.6
B48: IMPOSTE SUL REDDITO | C48: -327722.89
B49: RISULTATO NETTO | C49: =+C48+C47 -> 764686.75

Sheet Ricavi
B2: Consuntivo 2022 | J2: Budget vendite 2022
B3: Articolo | C3: Categoria | D3: Quantità (kg) | E3: P medio (€/kg) | F3: CMP medio (€/kg) | J3: Articolo | K3: Categoria | L3: Quantità (kg) | M3: P medio (€/kg) | N3: P medio ($/kg) | O3: CMP medio (€/kg) | P3: CMP medio ($/kg) | Q3: MP con dazio (6,5%)
B4: MP1 | C4: MP | D4: 20 | E4: =[1]Foglio1!U2 -> 10 | F4: =[1]Foglio1!V2 -> 7 | G4: =D4*F4 -> 140 | H4: =SUM(_xlfn.ANCHORARRAY(G4)) -> 140 | J4: MP1 | K4: MP | L4: 48000 | M4: 0.93 | O4: =P4*'CE 21-22'!$M$13*(1+$M$70) -> 0.59257692 | P4: 0.651 | Q4: x
B5: MP2 | C5: MP | D5: 98027.32 | E5: =[1]Foglio1!U3 -> 2.8454343 | F5: =[1]Foglio1!V3 -> 1.991804 | G5: =D5*F5 -> 195251.21 | J5: MP2 | K5: MP | L5: 700 | M5: 4 | O5: =P5*'CE 21-22'!$M$13*(1+$M$70) -> 2.5487179 | P5: 2.8 | Q5: x
B6: MP3 | C6: MP | D6: 42676.35 | E6: =[1]Foglio1!U4 -> 2.394192 | F6: =[1]Foglio1!V4 -> 1.6759344 | G6: =D6*F6 -> 71522.763 | J6: MP3 | K6: MP | L6: 1100 | M6: 2.4 | O6: =P6*'CE 21-22'!$M$13*(1+$M$70) -> 1.5292308 | P6: 1.68 | Q6: x
B7: MP4 | C7: MP | D7: 22386.52 | E7: =[1]Foglio1!U5 -> 1.6259024 | F7: =[1]Foglio1!V5 -> 1.1381317 | G7: =D7*F7 -> 25478.808 | J7: MP4 | K7: MP | L7: 125 | M7: 4 | O7: =P7*'CE 21-22'!$M$13*(1+$M$70) -> 2.5487179 | P7: 2.8 | Q7: x
B8: MP5 | C8: MP | D8: 7.54 | E8: =[1]Foglio1!U6 -> 7.3 | F8: =[1]Foglio1!V6 -> 5.11 | G8: =D8*F8 -> 38.5294 | J8: MP5 | K8: MP | L8: 1925 | M8: 2.9058442 | O8: =P8*'CE 21-22'!$M$13*(1+$M$70) -> 1.8515443 | P8: 2.0340909 | Q8: x
B9: MP6 | C9: MP | D9: 2430.33 | E9: =[1]Foglio1!U7 -> 1.4075385 | F9: =[1]Foglio1!V7 -> 0.98527697 | G9: =D9*F9 -> 2394.5482 | J9: MP6 | K9: MP | L9: 125 | M9: 4.4 | O9: =P9*'CE 21-22'!$M$13*(1+$M$70) -> 2.8035897 | P9: 3.08 | Q9: x
B10: MP7 | C10: MP | D10: 250 | E10: =[1]Foglio1!U8 -> 2.9 | F10: =[1]Foglio1!V8 -> 2.03 | G10: =D10*F10 -> 507.5 | J10: MP7 | K10: MP | L10: 2000 | M10: 4.62 | O10: =P10*'CE 21-22'!$M$13*(1+$M$70) -> 2.9437692 | P10: 3.234 | Q10: x
B11: MP8 | C11: MP | D11: 4269.45 | E11: =[1]Foglio1!U9 -> 2.0699911 | F11: =[1]Foglio1!V9 -> 1.4489938 | G11: =D11*F11 -> 6186.4064 | J11: MP8 | K11: MP | L11: 1000 | M11: 2.65 | O11: =P11*'CE 21-22'!$M$13*(1+$M$70) -> 1.6885256 | P11: 1.855 | Q11: x
B12: MP9 | C12: MP | D12: 4864.37 | E12: =[1]Foglio1!U10 -> 2.5294424 | F12: =[1]Foglio1!V10 -> 1.7706096 | G12: =D12*F12 -> 8612.9004 | J12: MP9 | K12: MP | L12: 7000 | M12: 0.19 | O12: 0.133
B13: MP10 | C13: MP | D13: 337.42 | E13: =[1]Foglio1!U11 -> 2.3872631 | F13: =[1]Foglio1!V11 -> 1.6710841 | G13: =D13*F13 -> 563.85721 | J13: MP10 | K13: MP | L13: 34866.4 | M13: 0.50710644 | O13: 0.35497451
B14: MP11 | C14: MP | D14: 157.97 | E14: =[1]Foglio1!U12 -> 1.4 | F14: =[1]Foglio1!V12 -> 0.98 | G14: =D14*F14 -> 154.8106 | J14: MP11 | K14: MP | L14: 14037.12 | M14: 7.4104529 | O14: 5.187317
B15: MP12 | C15: MP | D15: 8991.88 | E15: =[1]Foglio1!U13 -> 1.88 | F15: =[1]Foglio1!V13 -> 1.316 | G15: =D15*F15 -> 11833.314 | J15: MP12 | K15: MP | L15: 1904 | M15: 1.4275735 | O15: 0.99930147
B16: MP13 | C16: MP | D16: 83.57 | E16: =[1]Foglio1!U14 -> 1.13 | F16: =[1]Foglio1!V14 -> 0.791 | G16: =D16*F16 -> 66.10387 | J16: MP13 | K16: MP | L16: 150 | M16: 13 | O16: 9.1
B17: MP14 | C17: MP | D17: 1919.55 | E17: =[1]Foglio1!U15 -> 3.6564489 | F17: =[1]Foglio1!V15 -> 2.5595142 | G17: =D17*F17 -> 4913.1155 | J17: MP14 | K17: MP | L17: 20 | M17: 13.5 | O17: 9.45
B18: MP15 | C18: MP | D18: 29681.74 | E18: =[1]Foglio1!U16 -> 0.29851714 | F18: =[1]Foglio1!V16 -> 0.208962 | G18: =D18*F18 -> 6202.3556 | J18: PCL1 | K18: PCL | L18: 2160885 | M18: 0.11065878 | O18: 0.06
B19: MP16 | C19: MP | D19: 1390.97 | E19: =[1]Foglio1!U17 -> 1.3214683 | F19: =[1]Foglio1!V17 -> 0.92502778 | G19: =D19*F19 -> 1286.6859 | J19: PCL2 | K19: PCL | L19: 168325 | M19: 0.63902213 | O19: 0.45
B20: MP17 | C20: MP | D20: 10021.1 | E20: =[1]Foglio1!U18 -> 0.20188006 | F20: =[1]Foglio1!V18 -> 0.14131604 | G20: =D20*F20 -> 1416.1422 | J20: PCL3 | K20: PCL | L20: 495475 | M20: 1.6503165 | O20: 1.2250024
B21: MP18 | C21: MP | D21: 11225.39 | E21: =[1]Foglio1!U19 -> 3.4812737 | F21: =[1]Foglio1!V19 -> 2.4368916 | G21: =D21*F21 -> 27355.059 | J21: PCL4 | K21: PCL | L21: 489058 | M21: 2.681449 | O21: 2.2169886
B22: MP19 | C22: MP | D22: 5.18 | E22: =[1]Foglio1!U20 -> 5.1675676 | F22: =[1]Foglio1!V20 -> 3.6172973 | G22: =D22*F22 -> 18.7376 | J22: PCL5 | K22: PCL | L22: 6160 | M22: 2.25 | O22: 1.86435
B23: MP20 | C23: MP | D23: 0.17 | E23: =[1]Foglio1!U21 -> 0.45 | F23: =[1]Foglio1!V21 -> 0.315 | G23: =D23*F23 -> 0.05355 | J23: PF P1 | K23: PF | L23: 1719564 | M23: 3.2527356 | O23: 2.2970084
... B26: MP23 | C26: MP | D26: 40 | E26: =[1]Foglio1!U24 -> 3 | F26: =[1]Foglio1!V24 -> 2.1 | G26: =D26*F26 -> 84 | J26: PF P4 | K26: PF | L26: 8070474 | M26: 3.1339359 | O26: 2.1581977
B27: MP24 | C27: MP | D27: 11.82 | E27: =[1]Foglio1!U25 -> 12.98291 | F27: =[1]Foglio1!V25 -> 9.0880372 | G27: =D27*F27 -> 107.4206 | J27: PF P5 | K27: PF | L27: 205850 | M27: =N27*'CE 21-22'!$M$13 -> 2.688465 | N27: 3.145504 | O27: 2.1592931
B28: PCL1 | C28: PCL | D28: 1925163 | E28: =[1]Foglio1!U26 -> 0.077960604 | F28: =[1]Foglio1!V26 -> 0.38787648 | G28: =D28*F28 -> 746725.46 | J28: PF P6 | K28: PF | L28: 3233156 | M28: =N28*'CE 21-22'!$M$13 -> 2.7614723 | N28: 3.2309226 | O28: 2.2976852
B29: PCL2 | C29: PCL | D29: 258660 | E29: =[1]Foglio1!U27 -> 0.67441661 | F29: =[1]Foglio1!V27 -> 0.4836664 | G29: =D29*F29 -> 125105.15 | J29: PF P7 | K29: PF | L29: 660340 | M29: 0.96042054 | O29: 0.73562048
B30: PCL3 | C30: PCL | D30: 765278 | E30: =[1]Foglio1!U28 -> 1.5633914 | F30: =[1]Foglio1!V28 -> 0.97575994 | G30: =D30*F30 -> 746727.61 | J30: PF V1 | K30: PF | L30: 509668 | M30: 1.4659811 | O30: 1.1399042
B31: PCL4 | C31: PCL | D31: 209170 | E31: =[1]Foglio1!U29 -> 1.6736903 | F31: =[1]Foglio1!V29 -> 1.3705061 | G31: =D31*F31 -> 286668.76 | J31: PF V2 | K31: PF | L31: 2539984 | M31: 1.5574062 | O31: 1.1905015
B32: PCL5 | C32: PCL | D32: 65440 | E32: =[1]Foglio1!U30 -> 0.1 | F32: =[1]Foglio1!V30 -> 0 | G32: =D32*F32 -> 0 | J32: PF V3 | K32: PF | L32: 879638 | M32: 1.525531 | O32: 1.1595348
B33: PF P1 | C33: PF | D33: 15137 | E33: =[1]Foglio1!U31 -> 0.95151747 | F33: =[1]Foglio1!V31 -> 0 | G33: =D33*F33 -> 0 | J33: PF V4 | K33: PF | L33: 579689 | M33: 1.5588271 | O33: 1.1870108
B34: PF P2 | C34: PF | D34: 2654859 | E34: =[1]Foglio1!U32 -> 2.0941639 | F34: 1.58 | G34: =D34*F34 -> 4194677.2 | J34: PF V5 | K34: PF | L34: 448105 | M34: 1.4237469 | O34: 1.1223359
B35: PF P3 | C35: PF | D35: 326700 | E35: =[1]Foglio1!U33 -> 2.218292 | F35: =[1]Foglio1!V33 -> 1.5527802 | G35: =D35*F35 -> 507293.31 | J35: PF V6 | K35: PF | L35: 130100 | M35: 1.9231706 | O35: 1.248968
B36: PF P4 | C36: PF | D36: 1189375 | E36: =[1]Foglio1!U34 -> 2.1110997 | F36: =[1]Foglio1!V34 -> 1.5542674 | G36: =D36*F36 -> 1848606.7 | J36: PF V7 | K36: PF | L36: 13340 | M36: 1.188051 | O36: 0.55081495
B37: PF P5 | C37: PF | D37: 9796075 | E37: =[1]Foglio1!U35 -> 2.168379 | F37: 1.5 | G37: =D37*F37 -> 14694112 | J37: PF V8 | K37: PF | L37: 81820 | M37: 1.6966732 | O37: 1.2888625
B38: PF P6 | C38: PF | D38: 251400 | E38: =[1]Foglio1!U36 -> 2.4447673 | F38: =[1]Foglio1!V36 -> 1.6734553 | G38: =D38*F38 -> 420706.66 | J38: PF V9 | K38: PF | L38: 21040 | M38: 1.6010133 | O38: 1.3689428
B39: PF P7 | C39: PF | D39: 3850300 | E39: =[1]Foglio1!U37 -> 2.1755305 | F39: 1.5 | G39: =D39*F39 -> 5775450 | J39: PF V10 | K39: PF | L39: 14625 | M39: 1.6058974 | O39: 1.2319167
B40: PF P8 | C40: PF | D40: 558900 | E40: =[1]Foglio1!U38 -> 0.72040658 | F40: =[1]Foglio1!V38 -> 0.54555471 | G40: =D40*F40 -> 304910.53 | J40: PF V11 | K40: PF | L40: 307868 | M40: =N40*'CE 21-22'!$M$13 -> 0.90408699 | N40: 1.0577818 | O40: 0.75997645
B41: PF V1 | C41: PF | D41: 536830 | E41: =[1]Foglio1!U39 -> 1.2394066 | F41: =[1]Foglio1!V39 -> 0.91844443 | G41: =D41*F41 -> 493048.52 | J41: PF V12 | K41: PF | L41: 7000 | M41: =N41*'CE 21-22'!$M$13 -> 1.1868132 | N41: 1.3885714 | O41: 1.1206986
B42: PF V2 | C42: PF | D42: 2351569 | E42: =[1]Foglio1!U40 -> 1.3500109 | F42: 0.9 | G42: =D42*F42 -> 2116412.1 | J42: PF V13 | K42: PF | L42: 850145 | M42: =N42*'CE 21-22'!$M$13 -> 1.086341 | N42: 1.2710189 | O42: 0.99127781
B43: PF V3 | C43: PF | D43: 797082 | E43: =[1]Foglio1!U41 -> 1.1953138 | F43: =[1]Foglio1!V41 -> 0.89400995 | G43: =D43*F43 -> 712599.24 | J43: PF V14 | K43: PF | L43: 40480 | M43: =N43*'CE 21-22'!$M$13 -> 1.0868235 | N43: 1.2715835 | O43: 0.96538828
B44: PF V4 | C44: PF | D44: 917025 | E44: =[1]Foglio1!U42 -> 1.0664157 | F44: =[1]Foglio1!V42 -> 0.7840254 | G44: =D44*F44 -> 718970.89 | J44: PF V15 | K44: PF | L44: 30000 | M44: 2.1413333 | O44: 1.694168
B45: PF V5 | C45: PF | D45: 613690 | E45: =[1]Foglio1!U43 -> 1.0917239 | F45: =[1]Foglio1!V43 -> 0.85086393 | G45: =D45*F45 -> 522166.68 | J45: PF V16 | K45: PF | L45: 16500 | M45: 1.2007576 | O45: 0.92446038
B46: PF V6 | C46: PF | D46: 143085 | E46: =[1]Foglio1!U44 -> 1.5032278 | F46: =[1]Foglio1!V44 -> 0.80808671 | G46: =D46*F46 -> 115625.09 | J46: PF A1 | K46: PF | L46: 94290 | M46: 1.2885863 | O46: 0
B47: PF V7 | C47: PF | D47: 3675 | E47: =[1]Foglio1!U45 -> 0.81786395 | F47: =[1]Foglio1!V45 -> 0.51070224 | G47: =D47*F47 -> 1876.8308 | J47: PF A2 | K47: PF | L47: 151620 | M47: 1.7877721 | O47: 1.5182725
B48: PF V8 | C48: PF | D48: 222160 | E48: =[1]Foglio1!U46 -> 1.2292549 | F48: =[1]Foglio1!V46 -> 0.92105042 | G48: =D48*F48 -> 204620.56 | J48: PF A3 | K48: PF | L48: 411979 | M48: 1.8322973 | O48: 1.4404786
B49: PF V9 | C49: PF | D49: 38160 | E49: =[1]Foglio1!U47 -> 1.3103522 | F49: =[1]Foglio1!V47 -> 0.99331303 | G49: =D49*F49 -> 37904.825 | J49: PF A4 | K49: PF | L49: 1362839 | M49: =N49*'CE 21-22'!$M$13 -> 1.4234827 | N49: 1.6654747 | O49: 1.3105807
B50: PF V10 | C50: PF | D50: 30885 | E50: =[1]Foglio1!U48 -> 1.3809778 | F50: =[1]Foglio1!V48 -> 1.085102 | G50: =D50*F50 -> 33513.376 | J50: PF A5 | K50: PF | L50: 96425 | M50: =N50*'CE 21-22'!$M$13 -> 1.3552174 | N50: 1.5856044 | O50: 1.183724
B51: PF V11 | C51: PF | D51: 149758 | E51: =[1]Foglio1!U49 -> 0.76418956 | F51: =[1]Foglio1!V49 -> 0.5396053 | G51: =D51*F51 -> 80810.211 | J51: PF A6 | K51: PF | L51: 61100 | M51: =N51*'CE 21-22'!$M$13 -> 1.479173 | N51: 1.7306324 | O51: 1.2825348
B52: PF V12 | C52: PF | D52: 6000 | E52: =[1]Foglio1!U50 -> 1.2 | F52: =[1]Foglio1!V50 -> 0.87637 | G52: =D52*F52 -> 5258.22 | J52: PF A7 | K52: PF | L52: 2820459 | M52: 1.6397767 | O52: 1.2408624
B53: PF V13 | C53: PF | D53: 8000 | E53: =[1]Foglio1!U51 -> 1.29 | F53: =[1]Foglio1!V51 -> 0.935205 | G53: =D53*F53 -> 7481.64 | J53: PF A8 | K53: PF | L53: 157263 | M53: 1.6271923 | O53: 1.164888
B54: PF V14 | C54: PF | D54: 778210 | E54: =[1]Foglio1!U52 -> 1.0036049 | F54: =[1]Foglio1!V52 -> 0.76742587 | G54: =D54*F54 -> 597218.49 | J54: PF A9 | K54: PF | L54: 261930 | M54: 1.5522071 | O54: 1.034657
B55: PF V15 | C55: PF | D55: 30220 | E55: =[1]Foglio1!U53 -> 1.1262508 | F55: =[1]Foglio1!V53 -> 0.77318181 | G55: =D55*F55 -> 23365.554 | J55: PF A10 | K55: PF | L55: 500680 | M55: 1.2455093 | O55: 0.9001825
B56: PF V16 | C56: PF | D56: 25000 | E56: =[1]Foglio1!U54 -> 1.168 | F56: =[1]Foglio1!V54 -> 0.7948108 | G56: =D56*F56 -> 19870.27 | J56: PF A11 | K56: PF | L56: 62569 | M56: 1.9325903 | O56: 1.3611319
B57: PF V17 | C57: PF | D57: 41635 | E57: =[1]Foglio1!U55 -> 0.66185661 | F57: =[1]Foglio1!V55 -> 0.41639553 | G57: =D57*F57 -> 17336.628 | J57: PF A12 | K57: PF | L57: 927765 | M57: 2.0091657 | O57: 1.4048757
B58: PF A1 | C58: PF | D58: 51505 | E58: =[1]Foglio1!U56 -> 1.5481565 | F58: =[1]Foglio1!V56 -> 0 | G58: =D58*F58 -> 0 | J58: PF A13 | K58: PF | L58: 129425 | M58: 1.6307047 | O58: 1.1999951
B59: PF A2 | C59: PF | D59: 195860 | E59: =[1]Foglio1!U57 -> 1.0145298 | F59: =[1]Foglio1!V57 -> 1.321075 | G59: =D59*F59 -> 258745.75 | J59: PF A14 | K59: PF | L59: 131955 | M59: 1.9791818 | O59: 1.3700905
B60: PF A3 | C60: PF | D60: 648920 | E60: =[1]Foglio1!U58 -> 1.5966125 | F60: =[1]Foglio1!V58 -> 1.2557294 | G60: =D60*F60 -> 814867.95 | J60: PF A15 | K60: PF | L60: 375075 | M60: 1.786558 | O60: 1.2283679
B61: PF A4 | C61: PF | D61: 1660455 | E61: =[1]Foglio1!U59 -> 1.1722769 | F61: =[1]Foglio1!V59 -> 1.1783498 | G61: =D61*F61 -> 1956596.8 | J61: PF A16 | K61: PF | L61: 151110 | M61: 1.6128909 | O61: 1.1950273
B62: PF A5 | C62: PF | D62: 69185 | E62: =[1]Foglio1!U60 -> 1.3571836 | F62: =[1]Foglio1!V60 -> 1.0956718 | G62: =D62*F62 -> 75804.05 | J62: PF A17 | K62: PF | L62: 240225 | M62: 1.936526 | O62: 1.4175061
B63: PF A6 | C63: PF | D63: 55475 | E63: =[1]Foglio1!U61 -> 1.6094114 | F63: =[1]Foglio1!V61 -> 1.2580484 | G63: =D63*F63 -> 69790.234 | J63: PF A18 | K63: PF | L63: 392880 | M63: 1.0338126 | O63: 0.54367915
B64: PF A7 | C64: PF | D64: 2000669 | E64: =[1]Foglio1!U62 -> 1.7370299 | F64: =[1]Foglio1!V62 -> 1.2449452 | G64: =D64*F64 -> 2490723.4 | J64: PF A19 | K64: PF | L64: 1325620 | M64: 1.5992871 | O64: 1.4112719
B65: PF A8 | C65: PF | D65: 670980 | E65: =[1]Foglio1!U63 -> 1.6806899 | F65: =[1]Foglio1!V63 -> 1.1756714 | G65: =D65*F65 -> 788852.02 | J65: Spese trasporto | K65: Others | L65: 25000 | M65: €
B66: PF A9 | C66: PF | D66: 637940 | E66: =[1]Foglio1!U64 -> 1.0545723 | F66: =[1]Foglio1!V64 -> 0.80071437 | G66: =D66*F66 -> 510807.73 | J66: Premio Year22 | K66: Others | L66: 12 | M66: 18980.987
B67: PF A10 | C67: PF | D67: 535830 | E67: =[1]Foglio1!U65 -> 1.042733 | F67: =[1]Foglio1!V65 -> 0.71860724 | G67: =D67*F67 -> 385051.31
B68: PF A11 | C68: PF | D68: 108745 | E68: =[1]Foglio1!U66 -> 1.9287213 | F68: =[1]Foglio1!V66 -> 1.2761378 | G68: =D68*F68 -> 138773.6
B69: PF A12 | C69: PF | D69: 939305 | E69: =[1]Foglio1!U67 -> 1.9086575 | F69: =[1]Foglio1!V67 -> 1.3634691 | G69: =D69*F69 -> 1280713.3 | M69: Dazio
B70: PF A13 | C70: PF | D70: 115930 | E70: =[1]Foglio1!U68 -> 1.4443108 | F70: =[1]Foglio1!V68 -> 1.0710017 | G70: =D70*F70 -> 124161.23 | M70: =6.5*0.01 -> 0.065
B71: PF A14 | C71: PF | D71: 184065 | E71: =[1]Foglio1!U69 -> 1.9315133 | F71: =[1]Foglio1!V69 -> 1.3418995 | G71: =D71*F71 -> 246996.74
B72: PF A15 | C72: PF | D72: 484964 | E72: =[1]Foglio1!U70 -> 1.5090489 | F72: =[1]Foglio1!V70 -> 1.0507351 | G72: =D72*F72 -> 509568.71
B73: PF A16 | C73: PF | D73: 191590 | E73: =[1]Foglio1!U71 -> 1.5367825 | F73: =[1]Foglio1!V71 -> 1.1575221 | G73: =D73*F73 -> 221769.67
B74: PF A17 | C74: PF | D74: 160440 | E74: =[1]Foglio1!U72 -> 1.7941255 | F74: =[1]Foglio1!V72 -> 1.280412 | G74: =D74*F74 -> 205429.31
B75: PF A18 | C75: PF | D75: 229340 | E75: =[1]Foglio1!U73 -> 0.60202058 | F75: =[1]Foglio1!V73 -> 0.37323103 | G75: =D75*F75 -> 85596.804 | J75: =H76-'CE 21-22'!C5 -> -14423854
B76: PF A19 | C76: PF | D76: 786060 | E76: =[1]Foglio1!U74 -> 0.63365097 | F76: =[1]Foglio1!V74 -> 1.2438429 | G76: =D76*F76 -> 977735.18 | H76: =SUM(G2:G76) -> 46870806
B77: Spese trasporto | C77: Others | D77: 14 | E77: =[1]Foglio1!U76 -> 697.35714 | F77: =[1]Foglio1!V76 -> 0 | G77: =E77*D77 -> 9763 | H77: =H76-G78+G79-G77 -> 46918237
B78: Premio Year21 | C78: Others | D78: 15 | E78: =[1]Foglio1!U77 -> 19834.953 | F78: =[1]Foglio1!V77 -> 0 | G78: =E78*D78 -> 297524.29
B79: Addebiti vari | C79: Others | D79: 49573 | E79: =[1]Foglio1!U78 -> 7.1554838 | F79: =[1]Foglio1!V78 -> 0 | G79: =E79*D79 -> 354718.8
D80: qta | E80: €/qta
B81: NB:
B82: i) le spese di trasporto sono un riaccredito da parte di un cliente.
B83: ii) i premi vanno a diminuire il ricavo perché erogati a clienti

Sheet RicaviBudget
B2: Articolo | C2: Categoria | D2: Quantità Budget (kg) | E2: Prezzo Budget (€/kg) | F2: CMP euro/kg | G2: Ricavo Budget (€) | H2: Famiglia | I2: Note
B3: =Ricavi!J4 -> MP1 | C3: =Ricavi!K4 -> MP | D3: =Ricavi!L4 -> 48000 | E3: =Ricavi!M4 -> 0.93 | F3: =Ricavi!O4 -> 0.59257692 | G3: =D3*E3 -> 44640 | H3: MP
B4: =Ricavi!J5 -> MP2 | C4: =Ricavi!K5 -> MP | D4: =Ricavi!L5 -> 700 | E4: =Ricavi!M5 -> 4 | F4: =Ricavi!O5 -> 2.5487179 | G4: =D4*E4 -> 2800 | H4: MP
B5: =Ricavi!J6 -> MP3 | C5: =Ricavi!K6 -> MP | D5: =Ricavi!L6 -> 1100 | E5: =Ricavi!M6 -> 2.4 | F5: =Ricavi!O6 -> 1.5292308 | G5: =D5*E5 -> 2640 | H5: MP
B6: =Ricavi!J7 -> MP4 | C6: =Ricavi!K7 -> MP | D6: =Ricavi!L7 -> 125 | E6: =Ricavi!M7 -> 4 | F6: =Ricavi!O7 -> 2.5487179 | G6: =D6*E6 -> 500 | H6: MP
B7: =Ricavi!J8 -> MP5 | C7: =Ricavi!K8 -> MP | D7: =Ricavi!L8 -> 1925 | E7: =Ricavi!M8 -> 2.9058442 | F7: =Ricavi!O8 -> 1.8515443 | G7: =D7*E7 -> 5593.75 | H7: MP
B8: =Ricavi!J9 -> MP6 | C8: =Ricavi!K9 -> MP | D8: =Ricavi!L9 -> 125 | E8: =Ricavi!M9 -> 4.4 | F8: =Ricavi!O9 -> 2.8035897 | G8: =D8*E8 -> 550 | H8: MP
B9: =Ricavi!J10 -> MP7 | C9: =Ricavi!K10 -> MP | D9: =Ricavi!L10 -> 2000 | E9: =Ricavi!M10 -> 4.62 | F9: =Ricavi!O10 -> 2.9437692 | G9: =D9*E9 -> 9240 | H9: MP
B10: =Ricavi!J11 -> MP8 | C10: =Ricavi!K11 -> MP | D10: =Ricavi!L11 -> 1000 | E10: =Ricavi!M11 -> 2.65 | F10: =Ricavi!O11 -> 1.6885256 | G10: =D10*E10 -> 2650 | H10: MP
B11: =Ricavi!J12 -> MP9 | C11: =Ricavi!K12 -> MP | D11: =Ricavi!L12 -> 7000 | E11: =Ricavi!M12 -> 0.19 | F11: =Ricavi!O12 -> 0.133 | G11: =D11*E11 -> 1330 | H11: MP
B12: =Ricavi!J13 -> MP10 | C12: =Ricavi!K13 -> MP | D12: =Ricavi!L13 -> 34866.4 | E12: =Ricavi!M13 -> 0.50710644 | F12: =Ricavi!O13 -> 0.35497451 | G12: =D12*E12 -> 17680.976 | H12: MP
B13: =Ricavi!J14 -> MP11 | C13: =Ricavi!K14 -> MP | D13: =Ricavi!L14 -> 14037.12 | E13: =Ricavi!M14 -> 7.4104529 | F13: =Ricavi!O14 -> 5.187317 | G13: =D13*E13 -> 104021.42 | H13: MP
B14: =Ricavi!J15 -> MP12 | C14: =Ricavi!K15 -> MP | D14: =Ricavi!L15 -> 1904 | E14: =Ricavi!M15 -> 1.4275735 | F14: =Ricavi!O15 -> 0.99930147 | G14: =D14*E14 -> 2718.1 | H14: MP
B15: =Ricavi!J16 -> MP13 | C15: =Ricavi!K16 -> MP | D15: =Ricavi!L16 -> 150 | E15: =Ricavi!M16 -> 13 | F15: =Ricavi!O16 -> 9.1 | G15: =D15*E15 -> 1950 | H15: MP
B16: =Ricavi!J17 -> MP14 | C16: =Ricavi!K17 -> MP | D16: =Ricavi!L17 -> 20 | E16: =Ricavi!M17 -> 13.5 | F16: =Ricavi!O17 -> 9.45 | G16: =D16*E16 -> 270 | H16: MP | I16: =SUM(G22:G63) -> 68358549
B17: =Ricavi!J18 -> PCL1 | C17: =Ricavi!K18 -> PCL | D17: =Ricavi!L18 -> 2160885 | E17: =Ricavi!M18 -> 0.11065878 | F17: =Ricavi!O18 -> 0.06 | G17: =D17*E17 -> 239120.9 | H17: PCL
B18: =Ricavi!J19 -> PCL2 | C18: =Ricavi!K19 -> PCL | D18: =Ricavi!L19 -> 168325 | E18: =Ricavi!M19 -> 0.63902213 | F18: =Ricavi!O19 -> 0.45 | G18: =D18*E18 -> 107563.4 | H18: PCL
B19: =Ricavi!J20 -> PCL3 | C19: =Ricavi!K20 -> PCL | D19: =Ricavi!L20 -> 495475 | E19: =Ricavi!M20 -> 1.6503165 | F19: =Ricavi!O20 -> 1.2250024 | G19: =D19*E19 -> 817690.58 | H19: PCL
B20: =Ricavi!J21 -> PCL4 | C20: =Ricavi!K21 -> PCL | D20: =Ricavi!L21 -> 489058 | E20: =Ricavi!M21 -> 2.681449 | F20: =Ricavi!O21 -> 2.2169886 | G20: =D20*E20 -> 1311384.1 | H20: PCL
B21: =Ricavi!J22 -> PCL5 | C21: =Ricavi!K22 -> PCL | D21: =Ricavi!L22 -> 6160 | E21: =Ricavi!M22 -> 2.25 | F21: =Ricavi!O22 -> 1.86435 | G21: =D21*E21 -> 13860 | H21: PCL
B22: =Ricavi!J23 -> PF P1 | C22: =Ricavi!K23 -> PF | D22: =Ricavi!L23 -> 1719564 | E22: =Ricavi!M23 -> 3.2527356 | F22: =Ricavi!O23 -> 2.2970084 | G22: =D22*E22 -> 5593287 | H22: P | I22: Polveri P, consumi energia/metano diversi
B23: =Ricavi!J24 -> PF P2 | C23: =Ricavi!K24 -> PF | D23: =Ricavi!L24 -> 292499 | E23: =Ricavi!M24 -> 3.2730881 | F23: =Ricavi!O24 -> 2.252871 | G23: =D23*E23 -> 957375 | H23: P
B24: =Ricavi!J25 -> PF P3 | C24: =Ricavi!K25 -> PF | D24: =Ricavi!L25 -> 442800 | E24: =Ricavi!M25 -> 3.2317333 | F24: =Ricavi!O25 -> 2.2767847 | G24: =D24*E24 -> 1431011.5 | H24: P
B25: =Ricavi!J26 -> PF P4 | C25: =Ricavi!K26 -> PF | D25: =Ricavi!L26 -> 8070474 | E25: =Ricavi!M26 -> 3.1339359 | F25: =Ricavi!O26 -> 2.1581977 | G25: =D25*E25 -> 25292348 | H25: P
B26: =Ricavi!J27 -> PF P5 | C26: =Ricavi!K27 -> PF | D26: =Ricavi!L27 -> 205850 | E26: =Ricavi!M27 -> 2.688465 | F26: =Ricavi!O27 -> 2.1592931 | G26: =D26*E26 -> 553420.51 | H26: P
B27: =Ricavi!J28 -> PF P6 | C27: =Ricavi!K28 -> PF | D27: =Ricavi!L28 -> 3233156 | E27: =Ricavi!M28 -> 2.7614723 | F27: =Ricavi!O28 -> 2.2976852 | G27: =D27*E27 -> 8928270.9 | H27: P
B28: =Ricavi!J29 -> PF P7 | C28: =Ricavi!K29 -> PF | D28: =Ricavi!L29 -> 660340 | E28: =Ricavi!M29 -> 0.96042054 | F28: =Ricavi!O29 -> 0.73562048 | G28: =D28*E28 -> 634204.1 | H28: P
B29: =Ricavi!J30 -> PF V1 | C29: =Ricavi!K30 -> PF | D29: =Ricavi!L30 -> 509668 | E29: =Ricavi!M30 -> 1.4659811 | F29: =Ricavi!O30 -> 1.1399042 | G29: =D29*E29 -> 747163.65 | H29: V | I29: Polveri V, consumi medi diversi
B30: =Ricavi!J31 -> PF V2 | C30: =Ricavi!K31 -> PF | D30: =Ricavi!L31 -> 2539984 | E30: =Ricavi!M31 -> 1.5574062 | F30: =Ricavi!O31 -> 1.1905015 | G30: =D30*E30 -> 3955786.9 | H30: V
B31: =Ricavi!J32 -> PF V3 | C31: =Ricavi!K32 -> PF | D31: =Ricavi!L32 -> 879638 | E31: =Ricavi!M32 -> 1.525531 | F31: =Ricavi!O32 -> 1.1595348 | G31: =D31*E31 -> 1341915.1 | H31: V
B32: =Ricavi!J33 -> PF V4 | C32: =Ricavi!K33 -> PF | D32: =Ricavi!L33 -> 579689 | E32: =Ricavi!M33 -> 1.5588271 | F32: =Ricavi!O33 -> 1.1870108 | G32: =D32*E32 -> 903634.93 | H32: V
B33: =Ricavi!J34 -> PF V5 | C33: =Ricavi!K34 -> PF | D33: =Ricavi!L34 -> 448105 | E33: =Ricavi!M34 -> 1.4237469 | F33: =Ricavi!O34 -> 1.1223359 | G33: =D33*E33 -> 637988.1 | H33: V
B34: =Ricavi!J35 -> PF V6 | C34: =Ricavi!K35 -> PF | D34: =Ricavi!L35 -> 130100 | E34: =Ricavi!M35 -> 1.9231706 | F34: =Ricavi!O35 -> 1.248968 | G34: =D34*E34 -> 250204.5 | H34: V
B35: =Ricavi!J36 -> PF V7 | C35: =Ricavi!K36 -> PF | D35: =Ricavi!L36 -> 13340 | E35: =Ricavi!M36 -> 1.188051 | F35: =Ricavi!O36 -> 0.55081495 | G35: =D35*E35 -> 15848.6 | H35: V
B36: =Ricavi!J37 -> PF V8 | C36: =Ricavi!K37 -> PF | D36: =Ricavi!L37 -> 81820 | E36: =Ricavi!M37 -> 1.6966732 | F36: =Ricavi!O37 -> 1.2888625 | G36: =D36*E36 -> 138821.8 | H36: V
B37: =Ricavi!J38 -> PF V9 | C37: =Ricavi!K38 -> PF | D37: =Ricavi!L38 -> 21040 | E37: =Ricavi!M38 -> 1.6010133 | F37: =Ricavi!O38 -> 1.3689428 | G37: =D37*E37 -> 33685.32 | H37: V
B38: =Ricavi!J39 -> PF V10 | C38: =Ricavi!K39 -> PF | D38: =Ricavi!L39 -> 14625 | E38: =Ricavi!M39 -> 1.6058974 | F38: =Ricavi!O39 -> 1.2319167 | G38: =D38*E38 -> 23486.25 | H38: V
B39: =Ricavi!J40 -> PF V11 | C39: =Ricavi!K40 -> PF | D39: =Ricavi!L40 -> 307868 | E39: =Ricavi!M40 -> 0.90408699 | F39: =Ricavi!O40 -> 0.75997645 | G39: =D39*E39 -> 278339.45 | H39: V
B40: =Ricavi!J41 -> PF V12 | C40: =Ricavi!K41 -> PF | D40: =Ricavi!L41 -> 7000 | E40: =Ricavi!M41 -> 1.1868132 | F40: =Ricavi!O41 -> 1.1206986 | G40: =D40*E40 -> 8307.6923 | H40: V
B41: =Ricavi!J42 -> PF V13 | C41: =Ricavi!K42 -> PF | D41: =Ricavi!L42 -> 850145 | E41: =Ricavi!M42 -> 1.086341 | F41: =Ricavi!O42 -> 0.99127781 | G41: =D41*E41 -> 923547.33 | H41: V
... B44: =Ricavi!J45 -> PF V16 | C44: =Ricavi!K45 -> PF | D44: =Ricavi!L45 -> 16500 | E44: =Ricavi!M45 -> 1.2007576 | F44: =Ricavi!O45 -> 0.92446038 | G44: =D44*E44 -> 19812.5 | H44: V
B45: =Ricavi!J46 -> PF A1 | C45: =Ricavi!K46 -> PF | D45: =Ricavi!L46 -> 94290 | E45: =Ricavi!M46 -> 1.2885863 | F45: =Ricavi!O46 -> 0 | G45: =D45*E45 -> 121500.8 | H45: A | I45: Polveri A, consumi diversi dai primi due
B46: =Ricavi!J47 -> PF A2 | C46: =Ricavi!K47 -> PF | D46: =Ricavi!L47 -> 151620 | E46: =Ricavi!M47 -> 1.7877721 | F46: =Ricavi!O47 -> 1.5182725 | G46: =D46*E46 -> 271062 | H46: A
B47: =Ricavi!J48 -> PF A3 | C47: =Ricavi!K48 -> PF | D47: =Ricavi!L48 -> 411979 | E47: =Ricavi!M48 -> 1.8322973 | F47: =Ricavi!O48 -> 1.4404786 | G47: =D47*E47 -> 754868 | H47: A
B48: =Ricavi!J49 -> PF A4 | C48: =Ricavi!K49 -> PF | D48: =Ricavi!L49 -> 1362839 | E48: =Ricavi!M49 -> 1.4234827 | F48: =Ricavi!O49 -> 1.3105807 | G48: =D48*E48 -> 1939977.7 | H48: A
B49: =Ricavi!J50 -> PF A5 | C49: =Ricavi!K50 -> PF | D49: =Ricavi!L50 -> 96425 | E49: =Ricavi!M50 -> 1.3552174 | F49: =Ricavi!O50 -> 1.183724 | G49: =D49*E49 -> 130676.84 | H49: A
B50: =Ricavi!J51 -> PF A6 | C50: =Ricavi!K51 -> PF | D50: =Ricavi!L51 -> 61100 | E50: =Ricavi!M51 -> 1.479173 | F50: =Ricavi!O51 -> 1.2825348 | G50: =D50*E50 -> 90377.47 | H50: A
B51: =Ricavi!J52 -> PF A7 | C51: =Ricavi!K52 -> PF | D51: =Ricavi!L52 -> 2820459 | E51: =Ricavi!M52 -> 1.6397767 | F51: =Ricavi!O52 -> 1.2408624 | G51: =D51*E51 -> 4624923 | H51: A
B52: =Ricavi!J53 -> PF A8 | C52: =Ricavi!K53 -> PF | D52: =Ricavi!L53 -> 157263 | E52: =Ricavi!M53 -> 1.6271923 | F52: =Ricavi!O53 -> 1.164888 | G52: =D52*E52 -> 255897.15 | H52: A
B53: =Ricavi!J54 -> PF A9 | C53: =Ricavi!K54 -> PF | D53: =Ricavi!L54 -> 261930 | E53: =Ricavi!M54 -> 1.5522071 | F53: =Ricavi!O54 -> 1.034657 | G53: =D53*E53 -> 406569.6 | H53: A
B54: =Ricavi!J55 -> PF A10 | C54: =Ricavi!K55 -> PF | D54: =Ricavi!L55 -> 500680 | E54: =Ricavi!M55 -> 1.2455093 | F54: =Ricavi!O55 -> 0.9001825 | G54: =D54*E54 -> 623601.6 | H54: A | K54: Ricavi delle vendite di prodotti finiti
B55: =Ricavi!J56 -> PF A11 | C55: =Ricavi!K56 -> PF | D55: =Ricavi!L56 -> 62569 | E55: =Ricavi!M56 -> 1.9325903 | F55: =Ricavi!O56 -> 1.3611319 | G55: =D55*E55 -> 120920.24 | H55: A | K55: =SUMIF($C$3:$C$63,"PF",$G$3:$G$63) -> 68358549
B56: =Ricavi!J57 -> PF A12 | C56: =Ricavi!K57 -> PF | D56: =Ricavi!L57 -> 927765 | E56: =Ricavi!M57 -> 2.0091657 | F56: =Ricavi!O57 -> 1.4048757 | G56: =D56*E56 -> 1864033.6 | H56: A | K56: Ricavi delle vendite di materie prime
B57: =Ricavi!J58 -> PF A13 | C57: =Ricavi!K58 -> PF | D57: =Ricavi!L58 -> 129425 | E57: =Ricavi!M58 -> 1.6307047 | F57: =Ricavi!O58 -> 1.1999951 | G57: =D57*E57 -> 211053.95 | H57: A | K57: =SUMIF($C$3:$C$63,"MP",$G$3:$G$63) -> 196584.24
B58: =Ricavi!J59 -> PF A14 | C58: =Ricavi!K59 -> PF | D58: =Ricavi!L59 -> 131955 | E58: =Ricavi!M59 -> 1.9791818 | F58: =Ricavi!O59 -> 1.3700905 | G58: =D58*E58 -> 261162.93 | H58: A | K58: Ricavi conto lavorazione
B59: =Ricavi!J60 -> PF A15 | C59: =Ricavi!K60 -> PF | D59: =Ricavi!L60 -> 375075 | E59: =Ricavi!M60 -> 1.786558 | F59: =Ricavi!O60 -> 1.2283679 | G59: =D59*E59 -> 670093.25 | H59: A | K59: =SUMIF($C$3:$C$63,"PCL",$G$3:$G$63) -> 2489619
B60: =Ricavi!J61 -> PF A16 | C60: =Ricavi!K61 -> PF | D60: =Ricavi!L61 -> 151110 | E60: =Ricavi!M61 -> 1.6128909 | F60: =Ricavi!O61 -> 1.1950273 | G60: =D60*E60 -> 243723.95 | H60: A
B61: =Ricavi!J62 -> PF A17 | C61: =Ricavi!K62 -> PF | D61: =Ricavi!L62 -> 240225 | E61: =Ricavi!M62 -> 1.936526 | F61: =Ricavi!O62 -> 1.4175061 | G61: =D61*E61 -> 465201.95 | H61: A
B62: =Ricavi!J63 -> PF A18 | C62: =Ricavi!K63 -> PF | D62: =Ricavi!L63 -> 392880 | E62: =Ricavi!M63 -> 1.0338126 | F62: =Ricavi!O63 -> 0.54367915 | G62: =D62*E62 -> 406164.3 | H62: A
B63: =Ricavi!J64 -> PF A19 | C63: =Ricavi!K64 -> PF | D63: =Ricavi!L64 -> 1325620 | E63: =Ricavi!M64 -> 1.5992871 | F63: =Ricavi!O64 -> 1.4112719 | G63: =D63*E63 -> 2120047 | H63: A
B64: =Ricavi!J65 -> Spese trasporto | C64: =Ricavi!K65 -> Others | D64: =Ricavi!L65 -> 25000 | E64: 1 | F64: // | G64: =D64*E64 -> 25000 | I64: ="Riaccredito trasporti" -> Riaccredito trasporti
B65: =Ricavi!J66 -> Premio Year22 | C65: =Ricavi!K66 -> Others | D65: =Ricavi!L66 -> 12 | E65: =Ricavi!M66 -> 18980.987 | F65: // | G65: =-D65*E65 -> -227771.85 | I65: ="Premio clienti (ricavo negativo)" -> Premio clienti (ricavo negativo)
E67: Totale Ricavi Budget | G67: =SUM(G3:G65) -> 70841980

Sheet VariableCosts
B2: PREVISIONE COSTI VARIABILI 2022
B3: CONSUMI ENERGETICI FORECAST '22
B5: Consumi metano | C5: Cons specifico [smc/ton] | E5: Cons specifico [tonVAP /tonPF]
B6: PF A | E6: 0.93023256
B7: PF V | E7: 0.63953488
B8: PF P | E8: vedi note
B9: Consumi energia elettrica [kWh/ton]
B10: PF A | C10: 65
B11: PF V | C11: 60
B12: PF P | C12: 140
B13: Servizi Generali | C13: 275000 | D13: kWh /mese
B15: i) La vendita di polveri richiede la produzione di emulsioni viniliche, PF V, (*1,67) e i prodotti di conto lavoro sono processati nel reparto acriliche (per tutti i prodotti produzione=vendite).
B16: ii) il consumo di metano è considerato integralmente variabile (strettamente legato alla produzione). NB mentre le produzioni di polveri consumano direttamente metano, le produzioni di acriliche e viniliche consumano vapore.
B17: iii) il costo medio del metano è previsto in crescita rispetto al'anno precedente del 14%, mentre il costo medio dell'energia elettrica del 11%. Il costo delle componenti energetiche a bilancio è composto per il 41% da Energia elettrica. | P17: *a bilancio 2021
B18: iv) il consumo specifico per tonnellata di prodotto finito si può considerare costante tra 2021 e 2022. Nel 2021 sono stati spesi 3,45 mln € di costi energetici totali e sono stati consumati 8.997.222,22 kWh e 4.300.000 smc.
B19: v) dal nuovo anno, prevista riassegnazione quote CO2:le quote gratuite coprono il 75% delle quote totali, le rimanenti devono essere acquistate. Una quota di CO2 corrisponde ad una teonnellata di vapore e costa 71 €/ton.
B20: vi) per fare una tonnellata di vapore, servono 86 smc
B22: MATERIALI DI CONSUMO
B23: Costo previsto in aumento SUL 2021 solo per componente inflazione 2,5%
B25: PULIZIA E SMALTIMENTO RIFIUTI
B26: Il costo di smaltimento è stimabile in 10,24 euro per tonnellata di produzione solo sulle emulsioni.
B28: TRASPORTI E ONERI DI VENDITA
B29: i) i costi di trasporto sono da considerare solo per le vendite e non per gli acquisti.
B30: ii) Il costo di trasporto medio del 2021 per tonnellata di prodotto venduto è stato pari a 40 €/ton.
B31: ii) Visti i trend di crescita sul costo del metano, nel 2022 è previsto un aumento dei costi di trasporto di circa 8%.
B33: COSTO DI VENDITA - PROVVIGIONI
B34: Le provvigioni sono circa il 2% dell' imponibile di vendita delle solo polveri.

Sheet VariableCostsBudget
B2: Costo energia totale 2021 | C2: =3450000 -> 3450000
B3: % elettricità | C3: 0.41 | E3: Voce di costo | F3: quantita budget (kg) | G3: Quantità Budget (ton) | H3: Metano usato (smc) | I3: Energia elettrica usata (kWh)
B4: % metano | C4: =1-C3 -> 0.59 | E4: PF P | F4: =SUMIF(RicaviBudget!$H:$H,"P",RicaviBudget!$D:$D) -> 14624683 | G4: =F4/1000 -> 14624.683 | H4: =C23*G4*C24 -> 1343277.1 | I4: =G4*(C26+C22*C27) -> 3512848.9
B5: kWh 2021 | C5: 8997222.2 | E5: PF V | F5: =SUMIF(RicaviBudget!$H:$H,"V",RicaviBudget!$D:$D) -> 6470002 | G5: =F5/1000 -> 6470.002 | H5: =C21*G5*C24 -> 355850.11 | I5: =G5*C27 -> 388200.12
B6: smc metano 2021 | C6: 4300000 | E6: PF A | F6: =SUMIF(RicaviBudget!$H:$H,"A",RicaviBudget!$D:$CE)+SUMIF(RicaviBudget!$H:$H,"PCL",RicaviBudget!$D:$CE) -> 12975112 | G6: =F6/1000 -> 12975.112 | H6: =G6*C20*C24 -> 1038009 | I6: =G6*C28 -> 843382.28
E7: Totale PF | F7: =SUM(F4:F6) -> 34069797 | G7: =G6+G5+G4 -> 34069.797
B8: Costo elettricità 2021 | C8: =C2*C3 -> 1414500 | F8: Note | G8: Valore Budget (€) | H8: Formula/base di cacolo
B9: Costo Metano 2021 | C9: =C2*C4 -> 2035500 | F9: Costo metano | G9: =(H4+H5+H6)*C18 -> 1477079.6
F10: Costo energia elettrica | G10: =(I4+I5+I6+C30)*C17 -> 1403824.5
B11: Prezzo €/kWh 2021 | C11: =C8/C5 -> 0.15721519 | F11: Materiali di consumo | G11: =-'CE 21-22'!F15 *1.025 -> 153750
B12: Prezzo €/smc 2021 | C12: =C9/C6 -> 0.47337209 | F12: Pulizia e smaltimento rifiuti | G12: =(G5+G6+G4*C22)*C32 -> 449211.75
F13: Trasporti vendita | G13: =G7*C36 -> 1471815.2
B14: Aumento Elettricità 2022 | C14: 0.11 | F14: Provvigioni su vendite | G14: =(SUMIF(RicaviBudget!$H:$H,"P",RicaviBudget!$G:$G))*C38 -> 867798.34
B15: Aumento Metano 2022 | C15: 0.14 | F15: costo CO2 | G15: =C44*C45 -> 564932.18
B17: Prezzo €/kWh 2022 | C17: =C11*(1+C14) -> 0.17450886 | F17: Totale costi variabili | G17: =SUM(G9:G15) -> 6388411.7
B18: Prezzo €/smc 2022 | C18: =C12*(1+C15) -> 0.53964419
B20: cons vap per ton A | C20: =VariableCosts!E6 -> 0.93023256
B21: cons vap per ton V | C21: =VariableCosts!E7 -> 0.63953488
B22: ton di V per fare 1 Ton di P | C22: 1.67
B23: cons smc per ton P (comprese le v) | C23: =C22*C21 -> 1.0680233
B24: smc per ton vapore | C24: 86
B26: kWh per ton P (escluse le v) | C26: =VariableCosts!C12 -> 140
B27: kWh per ton V | C27: =VariableCosts!C11 -> 60
B28: kWh per ton A | C28: =VariableCosts!C10 -> 65
B29: kWh Servizi Generali mensile | C29: =VariableCosts!C13 -> 275000
B30: kWh Servizi Generali annui | C30: =C29*12 -> 3300000
B32: Costo smaltimento per ton di emulsione | C32: 10.24
B34: Costo trasporto per ton 2021 | C34: 40
B35: aumento costo trasporto 2022 | C35: 0.08
B36: Costo trasporto per ton 2022 | C36: =C34*(1+C35) -> 43.2
B38: provvigioni su vendite di polveri | C38: 0.02
B40: ton vapore PF P | C40: =G4*C23 -> 15619.502
B41: ton vapore V | C41: =G5*C21 -> 4137.792
B42: ton vapore A | C42: =G6*C20 -> 12069.872
B43: ton vapore tot | C43: =C41+C40+C42 -> 31827.165
B44: quote da acquistare | C44: =C43*0.25 -> 7956.7913
B45: costo per quota CO2 | C45: 71

Sheet FixedCosts
B2: PREVISIONE COSTI FISSI 2022
B3: COSTO DEL PERSONALE
B4: Costo in aumento rispetto al 2021 per aumenti da CCNL (in media 50€ mese per persona lordi per 100 persone).
B6: MANUTENZIONI
B7: Budget rivisto al ribasso di 150k€.
B9: ALTRI ONERI DEL PERSONALE
B10: In linea con 2021, costo previsto in aumento per prudenza del 2,5%
B12: ASSICURAZIONI
B13: In linea con 2021, costo previsto in aumento per prudenza del 2,5%
B15: CONSULENZE TECNICHE E CANONI ACQUE
B16: In linea con 2021, costo previsto in aumento per prudenza del 2,5%
B18: COSTO PER GODIMENTO DI BENI DI TERZI
... B28: In linea con 2021, costo previsto in aumento per prudenza del 2,5%

Sheet FixedCostsBudget
D2: Note
B3: Costo del personale | C3: =-'CE 21-22'!F22+50*12*100*1.4 -> 5594785.9 | D3: valore moltiplicato per 1.4 per via del folle cuneo fiscale italiano
B5: Manutenzioni | C5: =-'CE 21-22'!F23-150000 -> 1050000
B7: Altri oneri del personale | C7: =-'CE 21-22'!F24*1.025 -> 307500
B9: Assicurazioni | C9: =-'CE 21-22'!F25*1.025 -> 151700
B11: Consulenze tecniche e canoni acque | C11: =-'CE 21-22'!F26*1.025 -> 309550
B13: Costo per godimento di beni di terzi | C13: =-'CE 21-22'!F27*1.025 -> 212175
B15: Totale budget costi fissi di produzione | C15: =SUM(C13+C11+C9+C7+C5+C3) -> 7625710.9
B18: Consulenze e amministrazioni | C18: =-'CE 21-22'!F29*1.025 -> 563750
B20: Spese ufficio varie e oneri diversi di gestione | C20: =-'CE 21-22'!F30*1.025 -> 307500
B22: Imposte e tasse varie non sul reddito | C22: =-'CE 21-22'!F31*1.025 -> 102500
B24: Totale budget costi struttura comm./amm.va | C24: =SUM(C18+C20+C22) -> 973750
B27: TOTALE BUDGET COSTI FISSI | C27: =SUM(C24+C15) -> 8599460.9

Sheet Others
B2: PREVISIONE ALTRI COSTI 2022
B3: AMMORTAMENTI IMMOBILIZZAZIONI IMMATERIALI
B4: Nuovo investimento da ammortizzare da 750k€ in impianti e macchinari chimici | C4: *materiale, non immateriale
C5: ammoratamento 10 anni, non 10 % anno, ma circa 6.25% il primo anno, poi 8 anni 12.5 %, ultimo anno 6.25.
B6: AMMORTAMENTI IMMOBILIZZAZIONI MATERIALI | C6: *verificare il dato ma dovrebbe essere qeusto
B7: In linea con 2021.
B9: SVALUTAZIONE CREDITI
B10: Non sono previste svalutazioni credito.
B12: (ONERI FINANZIARI)
B13: Attivazione nuova linea di credito di 3 mln € dal 01.06.22 con tasso 5%/y | C13: *non importa quanti anni, noi guardiamo solo il primo | I13: poi fare *7/12 perche solo una parte
B15: PROVENTI FINANZIARI
B16: Non sono previsti proventi finanziari
B18: (ONERI STRAORDINARI)
B19: Non sono previsti oneri straordinari
B21: PROVENTI STRAORDINARI
B22: Non sono previsti proventi straordinari
B24: (SVALUTAZIONI-ACCANTONAMENTI)
B25: Non sono previsto svalutazioni e/o accantonamenti
B27: IMPOSTE SUL REDDITO
B28: 30% del risultato ante imposte

Sheet OthersBudget
D2: Note
B3: Ammortamenti immobilizzazioni immateriali | C3: =-'CE 21-22'!F34 -> 200000
B5: Ammortamenti immobilizzazioni materiali | C5: =-'CE 21-22'!F35 +C23*C24 -> 796875
B7: Svalutazione crediti | C7: 0
B9: Oneri finanziari | C9: =(3000000*0.05*7/12) -> 87500
B11: Proventi finanziari | C11: 0
B13: Oneri straordinari | C13: 0
B15: Proventi straordinari | C15: 0
B17: Svalutazioni-accantonamenti | C17: 0
B19: Imposte sul reddito | C19: ='CE Budget 2022'!C47*0.3 -> 602751.57 | D19: va calcolata dopo il CE budget, perché dipende dal margine operativo + finanziario
B23: nuovo investimento | C23: 750000
B24: quota primo anno | C24: 0.0625

Sheet CE Budget 2022
B2: FAR Polymers s.r.l. | D2: DELTA | E2: FAR Polymers s.r.l.
B3: CE mix totale 2022 | C3: CONSUNTIVO | E3: CE consuntivo 2022 | F3: CONSUNTIVO | P3: ora vanno fatti mix un po alla volta per capire da dove slatano fuori i delta
C4: Y1 | F4: Y1
B5: RICAVI DELLE VENDITE DI PRODOTTI FINITI | C5: =(SUMIF(RicaviBudget!$H:$H,"P",RicaviBudget!$G:$G)+SUMIF(RicaviBudget!$H:$H,"V",RicaviBudget!$G:$G)+SUMIF(RicaviBudget!$H:$H,"A",RicaviBudget!$G:$G)) -> 68358549 | D5: =C5-F5 -> 7063890 | E5: RICAVI DELLE VENDITE DI PRODOTTI FINITI | F5: 61294659
B6: RICAVI DELLE VENDITE DI MATERIE PRIME - RIADDEBITI MP A GAMMA | C6: =SUMIF(RicaviBudget!$H:$H,"MP",RicaviBudget!$G:$G) -> 196584.24 | D6: =C6-F6 -> -331642.38 | E6: RICAVI DELLE VENDITE DI MATERIE PRIME - RIADDEBITI MP A GAMMA | F6: 528226.63
B7: RICAVI CONTO LAVORAZIONE - GAMMA E POLIKEMIA | C7: =SUMIF(RicaviBudget!$H:$H,"PCL",RicaviBudget!$G:$G) -> 2489619 | D7: =C7-F7 -> 612028.61 | E7: RICAVI CONTO LAVORAZIONE - GAMMA E POLIKEMIA | F7: 1877590.4
B8: ALTRI RICAVI E LAVORI IN ECONOMIA | C8: =RicaviBudget!G64+RicaviBudget!G65 -> -202771.85 | D8: =C8-F8 -> -322771.85 | E8: ALTRI RICAVI E LAVORI IN ECONOMIA | F8: 120000
B9: VARIAZIONE PRODOTTI FINITI | C9: 0 | D9: =C9-F9 -> -500000 | E9: VARIAZIONE PRODOTTI FINITI | F9: 500000
B10: A) TOTALE RICAVI PRODUZIONE | C10: =+SUM(C5:C9) -> 70841980 | D10: =C10-F10 -> 6521504.4 | E10: A) TOTALE RICAVI PRODUZIONE | F10: 64320476 | P10: 1, dove vanno i costi tasse unione eruopea?
B11: ACQUISTO MATERIE PRIME | C11: {=-SUM(RicaviBudget!D3:D63 * RicaviBudget!F3:F63)} -> -52760561 | D11: =C11-F11 -> -3389755.4 | E11: ACQUISTO MATERIE PRIME | F11: -49370806
B12: VARIAZIONE SCORTE | C12: 0 | D12: =C12-F12 -> -2500000 | E12: VARIAZIONE SCORTE | F12: 2500000
B13: B) TOTALE COSTI MATERIE PRIME | C13: =+C11+C12 -> -52760561 | D13: =C13-F13 -> -5889755.4 | E13: B) TOTALE COSTI MATERIE PRIME | F13: -46870806
B14: COSTO ENERGIA TOTALE | C14: =-VariableCostsBudget!G9-VariableCostsBudget!G10-VariableCostsBudget!G15 -> -3445836.4 | D14: =C14-F14 -> 706871.14 | E14: COSTO ENERGIA TOTALE | F14: -4152707.5
B15: MATERIALI DI CONSUMO | C15: =-VariableCostsBudget!G11 -> -153750 | D15: =C15-F15 -> 21250 | E15: MATERIALI DI CONSUMO | F15: -175000
B16: PULIZIA E SMALTIMENTO RIFIUTI | C16: =-VariableCostsBudget!G12 -> -449211.75 | D16: =C16-F16 -> 70748.203 | E16: PULIZIA E SMALTIMENTO RIFIUTI | F16: -519959.95
B17: C) COSTI VARIABILI DI PRODUZIONE | C17: =SUM(C14:C16) -> -4048798.1 | D17: =C17-F17 -> 798869.34 | E17: C) COSTI VARIABILI DI PRODUZIONE | F17: -4847667.4
B18: TRASPORTI E ONERI DI VENDITA + ACQUISTO | C18: =-VariableCostsBudget!G13 -> -1471815.2 | D18: =C18-F18 -> -471815.23 | E18: TRASPORTI E ONERI DI VENDITA + ACQUISTO | F18: -1000000
B19: COSTO DI VENDITA - PROVVIGIONI-ENASARCO | C19: =-VariableCostsBudget!G14 -> -867798.34 | D19: =C19-F19 -> -317798.34 | E19: COSTO DI VENDITA - PROVVIGIONI-ENASARCO | F19: -550000
B20: D) TOTALE COSTI DI VENDITA | C20: =SUM(C18:C19) -> -2339613.6 | D20: =C20-F20 -> -789613.57 | E20: D) TOTALE COSTI DI VENDITA | F20: -1550000
B21: E) MARGINE OPERATIVO LORDO (A-B-C-D) | C21: =+C10+C13+C17+C20 -> 11693008 | D21: =C21-F21 -> 641004.77 | E21: E) MARGINE OPERATIVO LORDO (A-B-C-D) | F21: 11052003
B22: COSTO DEL PERSONALE | C22: =-FixedCostsBudget!C3 -> -5594785.9 | D22: =C22-F22 -> 55214.09 | E22: COSTO DEL PERSONALE | F22: -5650000
B23: MANUTENZIONI | C23: =-FixedCostsBudget!C5 -> -1050000 | D23: =C23-F23 -> 50000 | E23: MANUTENZIONI | F23: -1100000
B24: ALTRI ONERI DEL PERSONALE | C24: =-FixedCostsBudget!C7 -> -307500 | D24: =C24-F24 -> -2500 | E24: ALTRI ONERI DEL PERSONALE | F24: -305000
B25: ASSICURAZIONI | C25: =-FixedCostsBudget!C9 -> -151700 | D25: =C25-F25 -> -6700 | E25: ASSICURAZIONI | F25: -145000
B26: CONSULENZE TECNICHE E CANONI ACQUE | C26: =-FixedCostsBudget!C11 -> -309550 | D26: =C26-F26 -> -2550 | E26: CONSULENZE TECNICHE E CANONI ACQUE | F26: -307000
B27: COSTO PER GODIMENTO DI BENI DI TERZI | C27: =-FixedCostsBudget!C13 -> -212175 | D27: =C27-F27 -> -2675 | E27: COSTO PER GODIMENTO DI BENI DI TERZI | F27: -209500
B28: F) TOTALE COSTI FISSI DI PRODUZIONE | C28: =SUM(C22:C27) -> -7625710.9 | D28: =C28-F28 -> 90789.09 | E28: F) TOTALE COSTI FISSI DI PRODUZIONE | F28: -7716500
B29: CONSULENZE E AMMINISTRATORI | C29: =-FixedCostsBudget!C18 -> -563750 | D29: =C29-F29 -> -7750 | E29: CONSULENZE E AMMINISTRATORI | F29: -556000
B30: SPESE UFFICIO VARIE E ONERI DIVERSI DI GESTIONE | C30: =-FixedCostsBudget!C20 -> -307500 | D30: =C30-F30 -> -10500 | E30: SPESE UFFICIO VARIE E ONERI DIVERSI DI GESTIONE | F30: -297000
B31: IMPOSTE E TASSE VARIE NON SUL REDDITO | C31: =-FixedCostsBudget!C22 -> -102500 | D31: =C31-F31 -> -4500 | E31: IMPOSTE E TASSE VARIE NON SUL REDDITO | F31: -98000
B32: G) TOTALE COSTI STRUTTURA COMM./AMM.VA | C32: =SUM(C29:C31) -> -973750 | D32: =C32-F32 -> -22750 | E32: G) TOTALE COSTI STRUTTURA COMM./AMM.VA | F32: -951000
B33: H) REDDITO OPERATIVO (EBITDA) (E-F-G) | C33: =+C21+C28+C32 -> 3093546.9 | D33: =C33-F33 -> 709043.86 | E33: H) REDDITO OPERATIVO (EBITDA) (E-F-G) | F33: 2384503
B34: AMMORTAMENTI IMMOBILIZZAZIONI IMMATERIALI | C34: =-OthersBudget!C3 -> -200000 | D34: =C34-F34 -> -10000 | E34: AMMORTAMENTI IMMOBILIZZAZIONI IMMATERIALI | F34: -190000
B35: AMMORTAMENTI IMMOBILIZZAZIONI MATERIALI | C35: =-OthersBudget!C5 -> -796875 | D35: =C35-F35 -> 13125 | E35: AMMORTAMENTI IMMOBILIZZAZIONI MATERIALI | F35: -810000
B36: SVALUTAZIONE CREDITI | C36: =-OthersBudget!C7 -> 0 | D36: =C36-F36 -> 25000 | E36: SVALUTAZIONE CREDITI | F36: -25000
B37: I) TOTALE AMMORTAMENTI | C37: =SUM(C34:C36) -> -996875 | D37: =C37-F37 -> 28125 | E37: I) TOTALE AMMORTAMENTI | F37: -1025000
B38: L) MARGINE OPERATIVO NETTO (EBIT) (H-I) | C38: =+C33+C37 -> 2096671.9 | D38: =C38-F38 -> 737168.86 | E38: L) MARGINE OPERATIVO NETTO (EBIT) (H-I) | F38: 1359503
B39: (ONERI FINANZIARI) | C39: =-OthersBudget!C9 -> -87500 | D39: =C39-F39 -> 52633.04 | E39: (ONERI FINANZIARI) | F39: -140133.04
B40: PROVENTI FINANZIARI | C40: =OthersBudget!C11 -> 0 | D40: =C40-F40 -> -3543.62 | E40: PROVENTI FINANZIARI | F40: 3543.62
B41: M) ONERI E PROVENTI FINANZIARI NETTI | C41: =SUM(C39:C40) -> -87500 | D41: =C41-F41 -> 49089.42 | E41: M) ONERI E PROVENTI FINANZIARI NETTI | F41: -136589.42
B42: N) REDDITO OPERATIVO GESTIONE CARATTERISTICA (L-M) | C42: =+C38+C41 -> 2009171.9 | D42: =C42-F42 -> 786258.28 | E42: N) REDDITO OPERATIVO GESTIONE CARATTERISTICA (L-M) | F42: 1222913.6
B43: (ONERI STRAORDINARI) | C43: =-OthersBudget!C13 -> 0 | D43: =C43-F43 -> 130503.97 | E43: (ONERI STRAORDINARI) | F43: -130503.97
B44: PROVENTI STRAORDINARI | C44: =OthersBudget!C15 -> 0 | D44: =C44-F44 -> 0 | E44: PROVENTI STRAORDINARI | F44: 0
B45: (SVALUTAZIONI-ACCANTONAMENTI) | C45: =OthersBudget!C17 -> 0 | D45: =C45-F45 -> 0 | E45: (SVALUTAZIONI-ACCANTONAMENTI) | F45: 0
B46: O) ONERI E PROVENTI STRAORDINARI NETTI | C46: =SUM(C43:C45) -> 0 | D46: =C46-F46 -> 130503.97 | E46: O) ONERI E PROVENTI STRAORDINARI NETTI | F46: -130503.97
B47: P) RISULTATO ANTE IMPOSTE (N-O) | C47: =+C46+C42 -> 2009171.9 | D47: =C47-F47 -> 916762.25 | E47: P) RISULTATO ANTE IMPOSTE (N-O) | F47: 1092409.6
B48: IMPOSTE SUL REDDITO | C48: =-OthersBudget!C19 -> -602751.57 | D48: =C48-F48 -> -275028.67 | E48: IMPOSTE SUL REDDITO | F48: -327722.89
B49: RISULTATO NETTO | C49: =C47+C48 -> 1406420.3 | D49: =C49-F49 -> 641733.57 | E49: RISULTATO NETTO | F49: 764686.75

Sheet Analisi degli scostamenti
B2: Budget 2022 | F2: Categoria | G2: Mix Budget (%) | H2: Mix Standard | I2: Rapporto Totale famiglia-MS
B3: Categoria | C3: Volume (kg) | D3: Ricavi (€) | F3: MP | G3: =C4/$C$9 -> 0.003304372 | H3: =G3*$C$11 -> 127308.44 | I3: =C4/H3 -> 0.8872351
B4: MP | C4: =SUMIF(Ricavi!J:J, "MP*",Ricavi!L:L) -> 112952.52 | D4: {=SUMPRODUCT(--ISNUMBER((SEARCH("MP", Ricavi!$J$4:$J$64))), Ricavi!$L$4:$L$64, Ricavi!$M$4:$M$64)} -> 196584.24 | F4: PCL | G4: =C5/$C$9 -> 0.097122176 | H4: =G4*$C$11 -> 3741852.6 | I4: =C5/H4 -> 0.8872351
B5: PCL | C5: =SUMIF(Ricavi!J:J, "PCL*",Ricavi!L:L) -> 3319903 | D5: {=SUMPRODUCT(--ISNUMBER((SEARCH("PCL", Ricavi!$J$4:$J$64))), Ricavi!$L$4:$L$64, Ricavi!$M$4:$M$64)} -> 2489619 | F5: PF P | G5: =C6/$C$9 -> 0.42783811 | H5: =G5*$C$11 -> 16483436 | I5: =C6/H5 -> 0.8872351
B6: P | C6: =SUMIF(Ricavi!J:J, "PF P*",Ricavi!L:L) -> 14624683 | D6: {=SUMPRODUCT(--ISNUMBER((SEARCH("PF P", Ricavi!$J$4:$J$64))), Ricavi!$L$4:$L$64, Ricavi!$M$4:$M$64)} -> 43389917 | F6: PF V | G6: =C7/$C$9 -> 0.18927682 | H6: =G6*$C$11 -> 7292319.7 | I6: =C7/H6 -> 0.8872351
B7: V | C7: =SUMIF(Ricavi!J:J, "PF V*",Ricavi!L:L) -> 6470002 | D7: {=SUMPRODUCT(--ISNUMBER((SEARCH("PF V", Ricavi!$J$4:$J$64))), Ricavi!$L$4:$L$64, Ricavi!$M$4:$M$64)} -> 9386776.7 | F7: PF A | G7: =C8/$C$9 -> 0.28245852 | H7: =G7*$C$11 -> 10882357 | I7: =C8/H7 -> 0.8872351
B8: A | C8: =SUMIF(Ricavi!J:J, "PF A*",Ricavi!L:L) -> 9655209 | D8: {=SUMPRODUCT(--ISNUMBER((SEARCH("PF A", Ricavi!$J$4:$J$64))), Ricavi!$L$4:$L$64, Ricavi!$M$4:$M$64)} -> 15581855
B9: Totale budget | C9: =SUM(C4:C8) -> 34182750 | D9: =SUM(D4:D8) -> 71044752 | H9: =SUM(H3:H7) -> 38527274
B11: Totale reale | C11: =SUM(D14:D18) -> 38527274
B13: Voce | C13: Budget | D13: Reale | E13: ∆ Reale-Budget | F13: Mix Standard | G13: ∆ Mix Standard-Budget | H13: Mix Effettivo | I13: ∆ Mix Effettivo-Budget
A14: In kg | B14: Q MP | C14: =C4 -> 112952.52 | D14: =SUMIF(Ricavi!B:B, "MP*", Ricavi!D:D) -> 240574.55 | E14: =D14-C14 -> 127622.03 | F14: =H3 -> 127308.44 | G14: =F14-C14 -> 14355.924
B15: Q PCL | C15: =C5 -> 3319903 | D15: =SUMIF(Ricavi!B:B, "PCL*", Ricavi!D:D) -> 3223711 | E15: =D15-C15 -> -96192 | F15: =H4 -> 3741852.6 | G15: =F15-C15 -> 421949.63
B16: Q PF P | C16: =C6 -> 14624683 | D16: =SUMIF(Ricavi!B:B, "PF P*", Ricavi!D:D) -> 18642746 | E16: =D16-C16 -> 4018063 | F16: =H5 -> 16483436 | G16: =F16-C16 -> 1858753
B17: Q PF V | C17: =C7 -> 6470002 | D17: =SUMIF(Ricavi!B:B, "PF V*", Ricavi!D:D) -> 6692984 | E17: =D17-C17 -> 222982 | F17: =H6 -> 7292319.7 | G17: =F17-C17 -> 822317.68
B18: Q PF A | C18: =C8 -> 9655209 | D18: =SUMIF(Ricavi!B:B, "PF A*", Ricavi!D:D) -> 9727258 | E18: =D18-C18 -> 72049.01 | F18: =H7 -> 10882357 | G18: =F18-C18 -> 1227147.8
A20: In € | B20: Prezzo totale MP | C20: =#REF! -> #REF! | D20: =SUMIF(Ricavi!B:B, "MP*",Ricavi!E:E) -> 81.552496 | E20: =D20-C20 -> #REF!
B21: Prezzo totale PCL | C21: =#REF! -> #REF! | D21: =SUMIF([2]Ricavi!B:B, "PCL*",[2]Ricavi!E:E) -> #VALUE! | E21: =D21-C21 -> #VALUE!
B22: Prezzo totale PF P | C22: =#REF! -> #REF! | D22: =SUMIF([2]Ricavi!B:B, "PF P*",[2]Ricavi!E:E) -> #VALUE! | E22: =D22-C22 -> #VALUE!
B23: Prezzo totale PF V | C23: =#REF! -> #REF! | D23: =SUMIF([2]Ricavi!B:B, "PF V*",[2]Ricavi!E:E) -> #VALUE! | E23: =D23-C23 -> #VALUE!
B24: Prezzo totale PF A | C24: =#REF! -> #REF! | D24: =SUMIF([2]Ricavi!B:B, "PF A*",[2]Ricavi!E:E) -> #VALUE! | E24: =D24-C24 -> #VALUE!
B26: Ricavi totali MP | C26: =D4 -> 196584.24 | D26: {=SUMPRODUCT(--ISNUMBER((SEARCH("MP", Ricavi!$B$4:$B$76))), Ricavi!$D$4:$D$76, Ricavi!$E$4:$E$76)} -> 528226.63 | E26: =D26-C26 -> 331642.38 | F26: {=SUMPRODUCT(--ISNUMBER((SEARCH("MP", Ricavi!$B$4:$B$76))), Ricavi!$D$4:$D$76/I3, Ricavi!$M$4:$M$76)} -> 795930.13
B27: Ricavi totali PCL | C27: =D5 -> 2489619 | D27: {=SUMPRODUCT(--ISNUMBER((SEARCH("PCL", Ricavi!$B$4:$B$76))), Ricavi!$D$4:$D$76, Ricavi!$E$4:$E$76)} -> 1877590.4 | E27: =D27-C27 -> -612028.61 | F27: {=SUMPRODUCT(--ISNUMBER((SEARCH("MP", Ricavi!$B$4:$B$76))), Ricavi!$D$4:$D$76/I4, Ricavi!$M$4:$M$76)} -> 795930.13
B28: Ricavi totali PF P | C28: =D6 -> 43389917 | D28: {=SUMPRODUCT(--ISNUMBER((SEARCH("PF P", Ricavi!$B$4:$B$76))), Ricavi!$D$4:$D$76, Ricavi!$E$4:$E$76)} -> 39445017 | E28: =D28-C28 -> -3944900.5 | F28: {=SUMPRODUCT(--ISNUMBER((SEARCH("MP", Ricavi!$B$4:$B$76))), Ricavi!$D$4:$D$76/I5, Ricavi!$M$4:$M$76)} -> 795930.13
B29: Ricavi totali PF V | C29: =D7 -> 9386776.7 | D29: {=SUMPRODUCT(--ISNUMBER((SEARCH("PF V", Ricavi!$B$4:$B$76))), Ricavi!$D$4:$D$76, Ricavi!$E$4:$E$76)} -> 8028278.9 | E29: =D29-C29 -> -1358497.8 | F29: {=SUMPRODUCT(--ISNUMBER((SEARCH("MP", Ricavi!$B$4:$B$76))), Ricavi!$D$4:$D$76/I6, Ricavi!$M$4:$M$76)} -> 795930.13
B30: Ricavi totali PF A | C30: =D8 -> 15581855 | D30: {=SUMPRODUCT(--ISNUMBER((SEARCH("PF A", Ricavi!$B$4:$B$76))), Ricavi!$D$4:$D$76, Ricavi!$E$4:$E$76)} -> 13754406 | E30: =D30-C30 -> -1827449.2 | F30: {=SUMPRODUCT(--ISNUMBER((SEARCH("MP", Ricavi!$B$4:$B$76))), Ricavi!$D$4:$D$76/I7, Ricavi!$M$4:$M$76)} -> 795930.13
B32: Ricavi totali PF | C32: =SUM(C28:C30) -> 68358549 | D32: =SUM(D28:D30) -> 61227702 | E32: =D32-C32 -> -7130847.5
B33: Ricavi totali MP | C33: =C26 -> 196584.24 | D33: =D26 -> 528226.63 | E33: =D33-C33 -> 331642.38
B34: Ricavi totali PCL | C34: =C27 -> 2489619 | D34: =D27 -> 1877590.4 | E34: =D34-C34 -> -612028.61
B35: Altri ricavi | C35: =Ricavi!L65 - Ricavi!M66*Ricavi!L66 -> -202771.85 | D35: =SUM(Ricavi!E77*Ricavi!D77,Ricavi!D78*(-Ricavi!E78),Ricavi!D79*Ricavi!E79) -> 66957.51 | E35: =D35-C35 -> 269729.36
B36: Variazione prodotti | C36: 0 | D36: 500000 | E36: =D36-C36 -> 500000
B38: Totale ricavi di produzione | C38: =SUM(C32:C36) -> 70841980 | D38: =SUM(D32:D36) -> 64200476 | E38: =D38-C38 -> -6641504.4
B40: Acquisto MP | C40: {=-SUM(RicaviBudget!D3:D63*RicaviBudget!F3:F63)} -> -52760561 | D40: {=-SUM(Ricavi!D4:D76*Ricavi!F4:F76)} -> -46870806 | E40: =D40-C40 -> 5889755.4
B41: Variazione scorte | C41: 0 | D41: 0 | E41: =D41-C41 -> 0
B43: Totale costi materie prime | C43: =SUM(C40:C41) -> -52760561 | D43: =SUM(D40:D41) -> -46870806 | E43: =D43-C43 -> 5889755.4
B45: Costo energia totale | C45: ='CE Budget 2022'!C14 -> -3445836.4 | D45: ='CE Budget 2022'!F14 -> -4152707.5 | E45: =D45-C45 -> -706871.14
B46: Materiali di consumo | C46: ='CE Budget 2022'!C15 -> -153750 | D46: -175000 | E46: =D46-C46 -> -21250
B47: Puizia e smaltimento rifiuti | C47: ='CE Budget 2022'!C16 -> -449211.75 | D47: -519959.95 | E47: =D47-C47 -> -70748.203
B49: Costi variabili di produzione | C49: =SUM(C45:C47) -> -4048798.1 | D49: -4847667.4 | E49: =D49-C49 -> -798869.34
B51: Trasporti e oneri di vendita + acquisto | C51: ='CE Budget 2022'!C18 -> -1471815.2 | D51: -1000000 | E51: =D51-C51 -> 471815.23
B52: Costo di vendita- provvigion-enasarco | C52: ='CE Budget 2022'!C19 -> -867798.34 | D52: -550000 | E52: =D52-C52 -> 317798.34
B54: Totale costi di vendita | C54: =SUM(C51+C52) -> -2339613.6 | D54: -1550000 | E54: =D54-C54 -> 789613.57
B56: Margine operativo lordo (MON) | C56: =C38+C43+C49+C54 -> 11693008 | D56: =D38+D43+D49+D54 -> 10932003 | E56: =D56-C56 -> -761004.77
B57: Costo del personale | C57: =-FixedCostsBudget!C3 -> -5594785.9 | D57: ='CE Budget 2022'!F22 -> -5650000 | E57: =D57-C57 -> -55214.09
B58: Manutenzioni | C58: =-FixedCostsBudget!C5 -> -1050000 | D58: ='CE Budget 2022'!F23 -> -1100000 | E58: =D58-C58 -> -50000
B59: Altri oneri del personale | C59: =-FixedCostsBudget!C7 -> -307500 | D59: ='CE Budget 2022'!F24 -> -305000 | E59: =D59-C59 -> 2500
B60: Assicurazioni | C60: =-FixedCostsBudget!C9 -> -151700 | D60: ='CE Budget 2022'!F25 -> -145000 | E60: =D60-C60 -> 6700
B61: Consulenza tecniche e canoni acque | C61: =-FixedCostsBudget!C11 -> -309550 | D61: ='CE Budget 2022'!F26 -> -307000 | E61: =D61-C61 -> 2550
B62: Costo per godimento di beni terzi | C62: =-FixedCostsBudget!C13 -> -212175 | D62: ='CE Budget 2022'!F27 -> -209500 | E62: =D62-C62 -> 2675
B64: Totale costi fissi di produzione | C64: =SUM(C57:C62) -> -7625710.9 | D64: ='CE Budget 2022'!F28 -> -7716500 | E64: =D64-C64 -> -90789.09
B66: Consulenze e amministratori | C66: =-FixedCostsBudget!C18 -> -563750 | D66: ='CE Budget 2022'!F29 -> -556000 | E66: =D66-C66 -> 7750
B67: Spese ufficio varie e oneri diversi di gestione | C67: =-FixedCostsBudget!C20 -> -307500 | D67: ='CE Budget 2022'!F30 -> -297000 | E67: =D67-C67 -> 10500
B68: Imposte e tasse varie non sul reddito | C68: =-FixedCostsBudget!C22 -> -102500 | D68: ='CE Budget 2022'!F31 -> -98000 | E68: =D68-C68 -> 4500
B70: Totale costi struttura comm./amm.va | C70: =SUM(C66:C68) -> -973750 | D70: ='CE Budget 2022'!F32 -> -951000 | E70: =D70-C70 -> 22750
B71: Reddito operativo (EBITDA) | C71: =+C56+C64+C70 -> 3093546.9 | D71: ='CE Budget 2022'!F33 -> 2384503 | E71: =D71-C71 -> -709043.86
B73: AMMORTAMENTI IMMOBILIZZAZIONI IMMATERIALI | C73: =-OthersBudget!C3 -> -200000 | D73: ='CE Budget 2022'!F34 -> -190000 | E73: =D73-C73 -> 10000
B74: AMMORTAMENTI IMMOBILIZZAZIONI MATERIALI | C74: =-OthersBudget!C5 -> -796875 | D74: ='CE Budget 2022'!F35 -> -810000 | E74: =D74-C74 -> -13125
B75: SVALUTAZIONE CREDITI | C75: =-OthersBudget!C7 -> 0 | D75: ='CE Budget 2022'!F36 -> -25000 | E75: =D75-C75 -> -25000
B77: I) TOTALE AMMORTAMENTI | C77: =SUM(C73:C75) -> -996875 | D77: ='CE Budget 2022'!F37 -> -1025000 | E77: =D77-C77 -> -28125
B78: L) MARGINE OPERATIVO NETTO (EBIT) (H-I) | C78: =+C71+C77 -> 2096671.9 | D78: ='CE Budget 2022'!F38 -> 1359503 | E78: =D78-C78 -> -737168.86
B80: (ONERI FINANZIARI) | C80: =-OthersBudget!C9 -> -87500 | D80: ='CE Budget 2022'!F39 -> -140133.04 | E80: =D80-C80 -> -52633.04
B81: PROVENTI FINANZIARI | C81: =OthersBudget!C11 -> 0 | D81: ='CE Budget 2022'!F40 -> 3543.62 | E81: =D81-C81 -> 3543.62
B83: M) ONERI E PROVENTI FINANZIARI NETTI | C83: =SUM(C80:C81) -> -87500 | D83: ='CE Budget 2022'!F41 -> -136589.42 | E83: =D83-C83 -> -49089.42
B84: N) REDDITO OPERATIVO GESTIONE CARATTERISTICA (L-M) | C84: =+C78+C83 -> 2009171.9 | D84: ='CE Budget 2022'!F42 -> 1222913.6 | E84: =D84-C84 -> -786258.28
B85: (ONERI STRAORDINARI) | C85: =-OthersBudget!C13 -> 0 | D85: ='CE Budget 2022'!F43 -> -130503.97 | E85: =D85-C85 -> -130503.97
B86: PROVENTI STRAORDINARI | C86: =OthersBudget!C15 -> 0 | D86: ='CE Budget 2022'!F44 -> 0 | E86: =D86-C86 -> 0
B87: (SVALUTAZIONI-ACCANTONAMENTI) | C87: =OthersBudget!C17 -> 0 | D87: ='CE Budget 2022'!F45 -> 0 | E87: =D87-C87 -> 0
B89: O) ONERI E PROVENTI STRAORDINARI NETTI | C89: =SUM(C85:C87) -> 0 | D89: ='CE Budget 2022'!F46 -> -130503.97 | E89: =D89-C89 -> -130503.97
B90: P) RISULTATO ANTE IMPOSTE (N-O) | C90: =+C89+C84 -> 2009171.9 | D90: ='CE Budget 2022'!F47 -> 1092409.6 | E90: =D90-C90 -> -916762.25
B92: IMPOSTE SUL REDDITO | C92: =-OthersBudget!C19 -> -602751.57 | D92: ='CE Budget 2022'!F48 -> -327722.89 | E92: =D92-C92 -> 275028.67
B94: RISULTATO NETTO | C94: =C90+C92 -> 1406420.3 | D94: ='CE Budget 2022'!F49 -> 764686.75 | E94: =D94-C94 -> -641733.57

Sheet VariableCostsC
B2: Costo energia totale 2021 | C2: =3450000 -> 3450000
B3: % elettricità | C3: 0.41 | E3: Voce di costo | F3: quantita budget (kg) | G3: Quantità Budget (ton) | H3: Metano usato (smc) | I3: Energia elettrica usata (kWh)
B4: % metano | C4: =1-C3 -> 0.59 | E4: PF P | F4: =SUMIF(RicaviBudget!$H:$H,"P",RicaviBudget!$D:$D) -> 14624683 | G4: =F4/1000 -> 14624.683 | H4: =C23*G4*C24 -> 1343277.1 | I4: =G4*(C26+C22*C27) -> 3512848.9
B5: kWh 2021 | C5: 8997222.2 | E5: PF V | F5: =SUMIF(RicaviBudget!$H:$H,"V",RicaviBudget!$D:$D) -> 6470002 | G5: =F5/1000 -> 6470.002 | H5: =C21*G5*C24 -> 355850.11 | I5: =G5*C27 -> 388200.12
B6: smc metano 2021 | C6: 4300000 | E6: PF A | F6: =SUMIF(RicaviBudget!$H:$H,"A",RicaviBudget!$D:$CE)+SUMIF(RicaviBudget!$H:$H,"PCL",RicaviBudget!$D:$CE) -> 12975112 | G6: =F6/1000 -> 12975.112 | H6: =G6*C20*C24 -> 1038009 | I6: =G6*C28 -> 843382.28
E7: Totale PF | F7: =SUM(F4:F6) -> 34069797 | G7: =G6+G5+G4 -> 34069.797
B8: Costo elettricità 2021 | C8: =C2*C3 -> 1414500 | F8: Note | G8: Valore Budget (€) | H8: Formula/base di cacolo
B9: Costo Metano 2021 | C9: =C2*C4 -> 2035500 | F9: Costo metano | G9: =(H4+H5+H6)*C18 -> 1477079.6
F10: Costo energia elettrica | G10: =(I4+I5+I6+C30)*C17 -> 1403824.5
B11: Prezzo €/kWh 2021 | C11: =C8/C5 -> 0.15721519 | F11: Materiali di consumo | G11: =-'CE 21-22'!F15 *1.025 -> 153750
B12: Prezzo €/smc 2021 | C12: =C9/C6 -> 0.47337209 | F12: Pulizia e smaltimento rifiuti | G12: =(G5+G6+G4*C22)*C32 -> 449211.75
F13: Trasporti vendita | G13: =G7*C36 -> 1471815.2
B14: Aumento Elettricità 2022 | C14: 0.11 | F14: Provvigioni su vendite | G14: =(SUMIF(RicaviBudget!$H:$H,"P",RicaviBudget!$G:$G))*C38 -> 867798.34
B15: Aumento Metano 2022 | C15: 0.14 | F15: costo CO2 | G15: =C44*C45 -> 564932.18
B17: Prezzo €/kWh 2022 | C17: =C11*(1+C14) -> 0.17450886 | F17: Totale costi variabili | G17: =SUM(G9:G15) -> 6388411.7
B18: Prezzo €/smc 2022 | C18: =C12*(1+C15) -> 0.53964419
B20: cons vap per ton A | C20: =VariableCosts!E6 -> 0.93023256
B21: cons vap per ton V | C21: =VariableCosts!E7 -> 0.63953488
B22: ton di V per fare 1 Ton di P | C22: 1.67
B23: cons smc per ton P (comprese le v) | C23: =C22*C21 -> 1.0680233
B24: smc per ton vapore | C24: 86
B26: kWh per ton P (escluse le v) | C26: =VariableCosts!C12 -> 140
B27: kWh per ton V | C27: =VariableCosts!C11 -> 60
B28: kWh per ton A | C28: =VariableCosts!C10 -> 65
B29: kWh Servizi Generali mensile | C29: =VariableCosts!C13 -> 275000
B30: kWh Servizi Generali annui | C30: =C29*12 -> 3300000
B32: Costo smaltimento per ton di emulsione | C32: 10.24
B34: Costo trasporto per ton 2021 | C34: 40
B35: aumento costo trasporto 2022 | C35: 0.08
B36: Costo trasporto per ton 2022 | C36: =C34*(1+C35) -> 43.2
B38: provvigioni su vendite di polveri | C38: 0.02
B40: ton vapore PF P | C40: =G4*C23 -> 15619.502
B41: ton vapore V | C41: =G5*C21 -> 4137.792
B42: ton vapore A | C42: =G6*C20 -> 12069.872
B43: ton vapore tot | C43: =C41+C40+C42 -> 31827.165
B44: quote da acquistare | C44: =C43*0.25 -> 7956.7913
B45: costo per quota CO2 | C45: 71
